{"@context": "http://schema.org", "@type": "TVSeries", "url": "/title/tt8697870/", "name": "The Nevers", "image": "https://m.media-amazon.com/images/M/MV5BMjAzYjY1YTktMGIxMi00NzliLWEwMWUtNTQ1OTllZjE1NjJjXkEyXkFqcGdeQXVyMTEyMjM2NDc2._V1_.jpg", "genre": ["Drama", "Sci-Fi"], "actor": [{"@type": "Person", "url": "/name/nm0077397/", "name": "Elizabeth Berrington"}, {"@type": "Person", "url": "/name/nm0001035/", "name": "Ben Chaplin"}, {"@type": "Person", "url": "/name/nm12255173/", "name": "Brett Curtis"}, {"@type": "Person", "url": "/name/nm1683988/", "name": "Anna Devlin"}], "creator": [{"@type": "Person", "url": "/name/nm0923736/", "name": "Joss Whedon"}, {"@type": "Organization", "url": "/company/co0008693/"}, {"@type": "Organization", "url": "/company/co0242875/"}], "description": "The Nevers is a TV series starring Elizabeth Berrington, Ben Chaplin, and Brett Curtis. An epic tale following a gang of Victorian women who find themselves with unusual abilities, relentless enemies, and a mission that might change...", "datePublished": "2021-04-11", "keywords": "gang", "trailer": {"@type": "VideoObject", "name": "Official Teaser", "embedUrl": "/video/imdb/vi3713057049", "thumbnail": {"@type": "ImageObject", "contentUrl": "https://m.media-amazon.com/images/M/MV5BMWY3NDE3ZDMtMzZkYS00MTA1LWFjMTgtMDQ5MDE0YzFhZjdhXkEyXkFqcGdeQWFybm8@._V1_.jpg"}, "thumbnailUrl": "https://m.media-amazon.com/images/M/MV5BMWY3NDE3ZDMtMzZkYS00MTA1LWFjMTgtMDQ5MDE0YzFhZjdhXkEyXkFqcGdeQWFybm8@._V1_.jpg", "description": "In the last years of Victoria\u2019s reign, London is beset by the \u201cTouched\u201d: people \u2014 mostly women \u2014 who suddenly manifest abnormal abilities, some charming, some very disturbing. Among them are Amalia True (Laura Donnelly), a mysterious, quick-fisted widow, and Penance Adair (Ann Skelly), a brilliant young inventor. They are the champions of this new underclass, making a home for the Touched, while fighting the forces of\u2026 well, pretty much all the forces \u2014 to make room for those whom history as we know it has no place.", "uploadDate": "2021-02-02T17:43:28Z"}, "cast_and_character": [{"actor": {"@type": "Person", "url": "/name/nm0077397/?ref_=tt_cl_t1", "name": "Elizabeth Berrington"}, "character_and_episodes": [{"url": "/title/tt8697870/characters/nm0077397?ref_=tt_cl_t1", "name": "Lucy Best"}, {"url": "#", "name": "6 episodes, 2021"}]}, {"actor": {"@type": "Person", "url": "/name/nm12255173/?ref_=tt_cl_t3", "name": "Brett Curtis"}, "character_and_episodes": [{"url": "/title/tt8697870/characters/nm12255173?ref_=tt_cl_t3", "name": "George Thorns"}, {"url": "#", "name": "6 episodes, 2021"}]}, {"actor": {"@type": "Person", "url": "/name/nm1967827/?ref_=tt_cl_t5", "name": "Laura Donnelly"}, "character_and_episodes": [{"url": "/title/tt8697870/characters/nm1967827?ref_=tt_cl_t5", "name": "Amalia True"}, {"url": "#", "name": "6 episodes, 2021"}]}, {"actor": {"@type": "Person", "url": "/name/nm0296545/?ref_=tt_cl_t7", "name": "Nick Frost"}, "character_and_episodes": [{"url": "/title/tt8697870/characters/nm0296545?ref_=tt_cl_t7", "name": "Declan Orrun"}, {"url": "#", "name": "6 episodes, 2021"}]}, {"actor": {"@type": "Person", "url": "/name/nm11351736/?ref_=tt_cl_t9", "name": "Zain Hussain"}, "character_and_episodes": [{"url": "/title/tt8697870/characters/nm11351736?ref_=tt_cl_t9", "name": "Aneel"}, {"url": "#", "name": "6 episodes, 2021"}]}, {"actor": {"@type": "Person", "url": "/name/nm3938513/?ref_=tt_cl_t11", "name": "Zackary Momoh"}, "character_and_episodes": [{"url": "/title/tt8697870/characters/nm3938513?ref_=tt_cl_t11", "name": "Dr. Horatio Cousens"}, {"url": "#", "name": "6 episodes, 2021"}]}, {"actor": {"@type": "Person", "url": "/name/nm3584268/?ref_=tt_cl_t13", "name": "James Norton"}, "character_and_episodes": [{"url": "/title/tt8697870/characters/nm3584268?ref_=tt_cl_t13", "name": "Hugo Swann"}, {"url": "#", "name": "6 episodes, 2021"}]}, {"actor": {"@type": "Person", "url": "/name/nm10362084/?ref_=tt_cl_t15", "name": "Viola Prettejohn"}, "character_and_episodes": [{"url": "/title/tt8697870/characters/nm10362084?ref_=tt_cl_t15", "name": "Myrtle Haplisch"}, {"url": "#", "name": "6 episodes, 2021"}]}, {"actor": {"@type": "Person", "url": "/name/nm7584343/?ref_=tt_cl_t17", "name": "Kiran Sonia Sawar"}, "character_and_episodes": [{"url": "/title/tt8697870/characters/nm7584343?ref_=tt_cl_t17", "name": "Harriet Kaur"}, {"url": "#", "name": "6 episodes, 2021"}]}, {"actor": {"@type": "Person", "url": "/name/nm2119840/?ref_=tt_cl_t19", "name": "Ella Smith"}, "character_and_episodes": [{"url": "/title/tt8697870/characters/nm2119840?ref_=tt_cl_t19", "name": "Desir\u00e9e Blodgett"}, {"url": "#", "name": "6 episodes, 2021"}]}, {"actor": {"@type": "Person", "url": "/name/nm0868476/?ref_=tt_cl_t21", "name": "Pip Torrens"}, "character_and_episodes": [{"url": "/title/tt8697870/characters/nm0868476?ref_=tt_cl_t21", "name": "Lord Massen"}, {"url": "#", "name": "6 episodes, 2021"}]}, {"actor": {"@type": "Person", "url": "/name/nm3604902/?ref_=tt_cl_t23", "name": "Domenique Fragale"}, "character_and_episodes": [{"url": "/title/tt8697870/characters/nm3604902?ref_=tt_cl_t23", "name": "Beth Cassini"}, {"url": "#", "name": "5 episodes, 2021"}]}, {"actor": {"@type": "Person", "url": "/name/nm4981558/?ref_=tt_cl_t25", "name": "Tahlia Norrish"}, "character_and_episodes": [{"url": "/title/tt8697870/characters/nm4981558?ref_=tt_cl_t25", "name": "Touched"}, {"url": "#", "name": "4 episodes, 2021"}]}, {"actor": {"@type": "Person", "url": "/name/nm5103443/?ref_=tt_cl_t27", "name": "Grant Crookes"}, "character_and_episodes": [{"url": "/title/tt8697870/characters/nm5103443?ref_=tt_cl_t27", "name": "Ferryman's Gala Guest"}, {"url": "#", "name": "2 episodes, 2021"}]}, {"actor": {"@type": "Person", "url": "/name/nm10412946/?ref_=tt_cl_t29", "name": "Marek Lichtenberg"}, "character_and_episodes": [{"url": "/title/tt8697870/characters/nm10412946?ref_=tt_cl_t29", "name": "Lord Massen Thug"}, {"url": "#", "name": "2 episodes, 2021"}]}, {"actor": {"@type": "Person", "url": "/name/nm0001035/?ref_=tt_cl_t2", "name": "Ben Chaplin"}, "character_and_episodes": [{"url": "/title/tt8697870/characters/nm0001035?ref_=tt_cl_t2", "name": "Frank Mundi"}, {"url": "#", "name": "6 episodes, 2021"}]}, {"actor": {"@type": "Person", "url": "/name/nm1683988/?ref_=tt_cl_t4", "name": "Anna Devlin"}, "character_and_episodes": [{"url": "/title/tt8697870/characters/nm1683988?ref_=tt_cl_t4", "name": "Primrose Chattoway"}, {"url": "#", "name": "6 episodes, 2021"}]}, {"actor": {"@type": "Person", "url": "/name/nm7455038/?ref_=tt_cl_t6", "name": "Martyn Ford"}, "character_and_episodes": [{"url": "/title/tt8697870/characters/nm7455038?ref_=tt_cl_t6", "name": "Nicholas 'Odium' Perbal"}, {"url": "#", "name": "6 episodes, 2021"}]}, {"actor": {"@type": "Person", "url": "/name/nm11776337/?ref_=tt_cl_t8", "name": "Vinnie Heaven"}, "character_and_episodes": [{"url": "/title/tt8697870/characters/nm11776337?ref_=tt_cl_t8", "name": "Nimble"}, {"url": "#", "name": "6 episodes, 2021"}]}, {"actor": {"@type": "Person", "url": "/name/nm2240061/?ref_=tt_cl_t10", "name": "Amy Manson"}, "character_and_episodes": [{"url": "/title/tt8697870/characters/nm2240061?ref_=tt_cl_t10", "name": "Maladie"}, {"url": "#", "name": "6 episodes, 2021"}]}, {"actor": {"@type": "Person", "url": "/name/nm2406518/?ref_=tt_cl_t12", "name": "Rochelle Neil"}, "character_and_episodes": [{"url": "/title/tt8697870/characters/nm2406518?ref_=tt_cl_t12", "name": "Annie Carbey"}, {"url": "#", "name": "6 episodes, 2021"}]}, {"actor": {"@type": "Person", "url": "/name/nm0641354/?ref_=tt_cl_t14", "name": "Denis O'Hare"}, "character_and_episodes": [{"url": "/title/tt8697870/characters/nm0641354?ref_=tt_cl_t14", "name": "Dr. Edmund Hague"}, {"url": "#", "name": "6 episodes, 2021"}]}, {"actor": {"@type": "Person", "url": "/name/nm2068559/?ref_=tt_cl_t16", "name": "Tom Riley"}, "character_and_episodes": [{"url": "/title/tt8697870/characters/nm2068559?ref_=tt_cl_t16", "name": "Augustus 'Augie' Bidlow"}, {"url": "#", "name": "6 episodes, 2021"}]}, {"actor": {"@type": "Person", "url": "/name/nm7024798/?ref_=tt_cl_t18", "name": "Ann Skelly"}, "character_and_episodes": [{"url": "/title/tt8697870/characters/nm7024798?ref_=tt_cl_t18", "name": "Penance Adair"}, {"url": "#", "name": "6 episodes, 2021"}]}, {"actor": {"@type": "Person", "url": "/name/nm1870434/?ref_=tt_cl_t20", "name": "Eleanor Tomlinson"}, "character_and_episodes": [{"url": "/title/tt8697870/characters/nm1870434?ref_=tt_cl_t20", "name": "Mary Brighton"}, {"url": "#", "name": "6 episodes, 2021"}]}, {"actor": {"@type": "Person", "url": "/name/nm0931404/?ref_=tt_cl_t22", "name": "Olivia Williams"}, "character_and_episodes": [{"url": "/title/tt8697870/characters/nm0931404?ref_=tt_cl_t22", "name": "Lavinia Bidlow"}, {"url": "#", "name": "6 episodes, 2021"}]}, {"actor": {"@type": "Person", "url": "/name/nm1991065/?ref_=tt_cl_t24", "name": "Matt Emery"}, "character_and_episodes": [{"url": "/title/tt8697870/characters/nm1991065?ref_=tt_cl_t24", "name": "DI Birch"}, {"url": "#", "name": "4 episodes, 2021"}]}, {"actor": {"@type": "Person", "url": "/name/nm4378849/?ref_=tt_cl_t26", "name": "George Dawson"}, "character_and_episodes": [{"url": "/title/tt8697870/characters/nm4378849?ref_=tt_cl_t26", "name": "Arthur Twimble"}, {"url": "#", "name": "3 episodes, 2021"}]}, {"actor": {"@type": "Person", "url": "/name/nm7906653/?ref_=tt_cl_t28", "name": "Michael James"}, "character_and_episodes": [{"url": "/title/tt8697870/characters/nm7906653?ref_=tt_cl_t28", "name": "Teen Boy"}, {"url": "#", "name": "2 episodes, 2021"}]}, {"actor": {"@type": "Person", "url": "/name/nm11936434/?ref_=tt_cl_t30", "name": "Madeleine Wilson"}, "character_and_episodes": [{"url": "/title/tt8697870/characters/nm11936434?ref_=tt_cl_t30", "name": "Lady Whisper"}, {"url": "#", "name": "2 episodes, 2021"}]}]}