{"@context": "http://schema.org", "@type": "Movie", "url": "/title/tt0095705/", "name": "The Naked Gun: From the Files of Police Squad!", "image": "https://m.media-amazon.com/images/M/MV5BODk1ZWM4ZjItMjFhZi00MDMxLTgxNmYtODFhNWZlZTkwM2UwXkEyXkFqcGdeQXVyMTQxNzMzNDI@._V1_.jpg", "genre": ["Comedy", "Crime"], "contentRating": "PG-13", "actor": [{"@type": "Person", "url": "/name/nm0000558/", "name": "Leslie Nielsen"}, {"@type": "Person", "url": "/name/nm0001636/", "name": "Priscilla Presley"}, {"@type": "Person", "url": "/name/nm0001740/", "name": "O.J. Simpson"}, {"@type": "Person", "url": "/name/nm0001544/", "name": "Ricardo Montalban"}], "director": {"@type": "Person", "url": "/name/nm0001878/", "name": "David Zucker"}, "creator": [{"@type": "Person", "url": "/name/nm0958387/", "name": "Jerry Zucker"}, {"@type": "Person", "url": "/name/nm0000720/", "name": "Jim Abrahams"}, {"@type": "Person", "url": "/name/nm0001878/", "name": "David Zucker"}, {"@type": "Person", "url": "/name/nm0698493/", "name": "Pat Proft"}, {"@type": "Person", "url": "/name/nm0000720/", "name": "Jim Abrahams"}, {"@type": "Person", "url": "/name/nm0001878/", "name": "David Zucker"}, {"@type": "Person", "url": "/name/nm0958387/", "name": "Jerry Zucker"}, {"@type": "Organization", "url": "/company/co0023400/"}], "description": "The Naked Gun: From the Files of Police Squad! is a movie starring Leslie Nielsen, Priscilla Presley, and O.J. Simpson. Incompetent police Detective Frank Drebin must foil an attempt to assassinate Queen Elizabeth II.", "datePublished": "1988-12-02", "keywords": "police detective,spoof,slapstick comedy,parody,assassin", "aggregateRating": {"@type": "AggregateRating", "ratingCount": 154219, "bestRating": "10.0", "worstRating": "1.0", "ratingValue": "7.6"}, "review": {"@type": "Review", "itemReviewed": {"@type": "CreativeWork", "url": "/title/tt0095705/"}, "author": {"@type": "Person", "name": "SmileysWorld"}, "dateCreated": "2005-01-04", "inLanguage": "English", "name": "Great blend of slapstick and one-liners", "reviewBody": "I suppose when it comes down to it,I am very easily entertained when it comes to comedy.It just doesn't take much to make me laugh.The makers of The Naked Gun did their job well.The film is so overloaded with sight gags,that if you blink,you just might miss one,or maybe even two of them.The slightest distractions will make you miss something.Some of the humor is vulgar and downright tasteless,but nonetheless funny.The final sequences involving the baseball game were the best.With the possible exception of O.J.Simpson,who was never good when he tried to act,this was a grand all around comedic effort,and comedy,as many have said,is hard to produce.I actually can recall the short lived television series that this film is based on.Only six episodes were produced,and it was a shame more were not made.I was glad to see it come roaring back on the big screen.Perhaps it belonged there all along.", "reviewRating": {"@type": "Rating", "worstRating": "1", "bestRating": "10", "ratingValue": "8"}}, "duration": "PT1H25M", "trailer": {"@type": "VideoObject", "name": "The Naked Gun", "embedUrl": "/video/imdb/vi3084976409", "thumbnail": {"@type": "ImageObject", "contentUrl": "https://m.media-amazon.com/images/M/MV5BY2JmNDZhYTAtM2EzNy00OGVlLTgxM2YtOWRhMmY5OTA4MGQ0XkEyXkFqcGdeQXVyNzU1NzE3NTg@._V1_.jpg"}, "thumbnailUrl": "https://m.media-amazon.com/images/M/MV5BY2JmNDZhYTAtM2EzNy00OGVlLTgxM2YtOWRhMmY5OTA4MGQ0XkEyXkFqcGdeQXVyNzU1NzE3NTg@._V1_.jpg", "description": "Theatrical Trailer from Paramount", "uploadDate": "2008-04-18T11:55:43Z"}, "cast_and_character": [{"actor": {"@type": "Person", "url": "/name/nm0000558/?ref_=tt_cl_t1", "name": "Leslie Nielsen"}, "character_and_episodes": [{"url": "/title/tt0095705/characters/nm0000558?ref_=tt_cl_t1", "name": "Frank Drebin"}]}, {"actor": {"@type": "Person", "url": "/name/nm0001544/?ref_=tt_cl_t3", "name": "Ricardo Montalban"}, "character_and_episodes": [{"url": "/title/tt0095705/characters/nm0001544?ref_=tt_cl_t3", "name": "Vincent Ludwig"}]}, {"actor": {"@type": "Person", "url": "/name/nm0001740/?ref_=tt_cl_t5", "name": "O.J. Simpson"}, "character_and_episodes": [{"url": "/title/tt0095705/characters/nm0001740?ref_=tt_cl_t5", "name": "Nordberg"}]}, {"actor": {"@type": "Person", "url": "/name/nm0545408/?ref_=tt_cl_t7", "name": "Nancy Marchand"}, "character_and_episodes": [{"url": "/title/tt0095705/characters/nm0545408?ref_=tt_cl_t7", "name": "Mayor"}]}, {"actor": {"@type": "Person", "url": "/name/nm0153055/?ref_=tt_cl_t9", "name": "Jeannette Charles"}, "character_and_episodes": [{"url": "/title/tt0095705/characters/nm0153055?ref_=tt_cl_t9", "name": "Queen Elizabeth II"}]}, {"actor": {"@type": "Person", "url": "/name/nm0864096/?ref_=tt_cl_t11", "name": "Tiny Ron"}, "character_and_episodes": [{"url": "/title/tt0095705/characters/nm0864096?ref_=tt_cl_t11", "name": "Al"}]}, {"actor": {"@type": "Person", "url": "/name/nm0537447/?ref_=tt_cl_t13", "name": "Leslie Maier"}, "character_and_episodes": [{"url": "/title/tt0095705/characters/nm0537447?ref_=tt_cl_t13", "name": "'Weird Leslie'"}]}, {"actor": {"@type": "Person", "url": "/name/nm0341055/?ref_=tt_cl_t15", "name": "Joe Grifasi"}, "character_and_episodes": [{"url": "/title/tt0095705/characters/nm0341055?ref_=tt_cl_t15", "name": "Foreman"}]}, {"actor": {"@type": "Person", "url": "/name/nm0001636/?ref_=tt_cl_t2", "name": "Priscilla Presley"}, "character_and_episodes": [{"url": "/title/tt0095705/characters/nm0001636?ref_=tt_cl_t2", "name": "Jane Spencer"}]}, {"actor": {"@type": "Person", "url": "/name/nm0001421/?ref_=tt_cl_t4", "name": "George Kennedy"}, "character_and_episodes": [{"url": "/title/tt0095705/characters/nm0001421?ref_=tt_cl_t4", "name": "Ed Hocken"}]}, {"actor": {"@type": "Person", "url": "/name/nm0064277/?ref_=tt_cl_t6", "name": "Susan Beaubian"}, "character_and_episodes": [{"url": "/title/tt0095705/characters/nm0064277?ref_=tt_cl_t6", "name": "Mrs. Nordberg"}]}, {"actor": {"@type": "Person", "url": "/name/nm0083541/?ref_=tt_cl_t8", "name": "Raye Birk"}, "character_and_episodes": [{"url": "/title/tt0095705/characters/nm0083541?ref_=tt_cl_t8", "name": "Pahpshmir"}]}, {"actor": {"@type": "Person", "url": "/name/nm0930506/?ref_=tt_cl_t10", "name": "Ed Williams"}, "character_and_episodes": [{"url": "/title/tt0095705/characters/nm0930506?ref_=tt_cl_t10", "name": "Ted Olsen"}]}, {"actor": {"@type": "Person", "url": "/name/nm0946148/?ref_=tt_cl_t12", "name": "'Weird Al' Yankovic"}, "character_and_episodes": [{"url": "/title/tt0095705/characters/nm0946148?ref_=tt_cl_t12", "name": "'Weird Al'"}]}, {"actor": {"@type": "Person", "url": "/name/nm0293242/?ref_=tt_cl_t14", "name": "Winifred Freedman"}, "character_and_episodes": [{"url": "/title/tt0095705/characters/nm0293242?ref_=tt_cl_t14", "name": "Stephie"}]}]}