{"@context": "http://schema.org", "@type": "TVSeries", "url": "/title/tt1842530/", "name": "Unforgettable", "image": "https://m.media-amazon.com/images/M/MV5BMTYwMzU5NDM5Ml5BMl5BanBnXkFtZTcwMjkyOTYzNg@@._V1_.jpg", "genre": ["Crime", "Drama", "Mystery"], "contentRating": "TV-14", "actor": [{"@type": "Person", "url": "/name/nm0599889/", "name": "Poppy Montgomery"}, {"@type": "Person", "url": "/name/nm0909620/", "name": "Dylan Walsh"}, {"@type": "Person", "url": "/name/nm1620756/", "name": "James Hiroyuki Liao"}, {"@type": "Person", "url": "/name/nm0004852/", "name": "Jane Curtin"}], "creator": [{"@type": "Person", "url": "/name/nm0069257/", "name": "John Bellucci"}, {"@type": "Person", "url": "/name/nm0714959/", "name": "Ed Redlich"}, {"@type": "Organization", "url": "/company/co0280908/"}, {"@type": "Organization", "url": "/company/co0274041/"}, {"@type": "Organization", "url": "/company/co0086397/"}, {"@type": "Organization", "url": "/company/co0190449/"}], "description": "Unforgettable is a TV series starring Poppy Montgomery, Dylan Walsh, and James Hiroyuki Liao. Carrie Wells, a former police detective, has a rare ability to remember virtually everything she experiences including detailed visual...", "datePublished": "2011-09-20", "keywords": "young woman,usa,united states,criminal investigation,murder investigation", "aggregateRating": {"@type": "AggregateRating", "ratingCount": 16948, "bestRating": "10.0", "worstRating": "1.0", "ratingValue": "6.7"}, "review": {"@type": "Review", "itemReviewed": {"@type": "CreativeWork", "url": "/title/tt1842530/"}, "author": {"@type": "Person", "name": "debb-34918"}, "dateCreated": "2020-09-15", "inLanguage": "English", "name": "Jane Curtain", "reviewBody": "I like all the actors in this series, especially like Jane Curtain. I've only seen her in comedy previously which she was great at, but she also plays a serious role absolutely amazing!", "reviewRating": {"@type": "Rating", "worstRating": "1", "bestRating": "10", "ratingValue": "7"}}, "trailer": {"@type": "VideoObject", "name": "Unforgettable: The Haircut", "embedUrl": "/video/imdb/vi602651929", "thumbnail": {"@type": "ImageObject", "contentUrl": "https://m.media-amazon.com/images/M/MV5BNTUxMzdkY2QtZGJiMS00MjUzLWFhNTUtNWRkMTI0ZDVlMjA0XkEyXkFqcGdeQXRyYW5zY29kZS13b3JrZmxvdw@@._V1_.jpg"}, "thumbnailUrl": "https://m.media-amazon.com/images/M/MV5BNTUxMzdkY2QtZGJiMS00MjUzLWFhNTUtNWRkMTI0ZDVlMjA0XkEyXkFqcGdeQXRyYW5zY29kZS13b3JrZmxvdw@@._V1_.jpg", "description": "Unforgettable: The Haircut", "uploadDate": "2019-04-04T21:24:02Z"}, "cast_and_character": [{"actor": {"@type": "Person", "url": "/name/nm0599889/?ref_=tt_cl_t1", "name": "Poppy Montgomery"}, "character_and_episodes": [{"url": "/title/tt1842530/characters/nm0599889?ref_=tt_cl_t1", "name": "Carrie Wells"}, {"url": "#", "name": "61 episodes, 2011-2016"}]}, {"actor": {"@type": "Person", "url": "/name/nm1620756/?ref_=tt_cl_t3", "name": "James Hiroyuki Liao"}, "character_and_episodes": [{"url": "/title/tt1842530/characters/nm1620756?ref_=tt_cl_t3", "name": "Jay Lee"}, {"url": "#", "name": "39 episodes, 2013-2016"}]}, {"actor": {"@type": "Person", "url": "/name/nm1316767/?ref_=tt_cl_t5", "name": "Dallas Roberts"}, "character_and_episodes": [{"url": "/title/tt1842530/characters/nm1316767?ref_=tt_cl_t5", "name": "Eliot Delson"}, {"url": "#", "name": "28 episodes, 2013-2015"}]}, {"actor": {"@type": "Person", "url": "/name/nm0309461/?ref_=tt_cl_t7", "name": "Michael Gaston"}, "character_and_episodes": [{"url": "/title/tt1842530/characters/nm0309461?ref_=tt_cl_t7", "name": "Mike Costello"}, {"url": "#", "name": "22 episodes, 2011-2012"}]}, {"actor": {"@type": "Person", "url": "/name/nm0883173/?ref_=tt_cl_t9", "name": "Daya Vaidya"}, "character_and_episodes": [{"url": "/title/tt1842530/characters/nm0883173?ref_=tt_cl_t9", "name": "Nina Inara"}, {"url": "#", "name": "22 episodes, 2011-2012"}]}, {"actor": {"@type": "Person", "url": "/name/nm0909620/?ref_=tt_cl_t2", "name": "Dylan Walsh"}, "character_and_episodes": [{"url": "/title/tt1842530/characters/nm0909620?ref_=tt_cl_t2", "name": "Al Burns"}, {"url": "#", "name": "61 episodes, 2011-2016"}]}, {"actor": {"@type": "Person", "url": "/name/nm0004852/?ref_=tt_cl_t4", "name": "Jane Curtin"}, "character_and_episodes": [{"url": "/title/tt1842530/characters/nm0004852?ref_=tt_cl_t4", "name": "Joanne Webster"}, {"url": "#", "name": "35 episodes, 2012-2014"}]}, {"actor": {"@type": "Person", "url": "/name/nm0194241/?ref_=tt_cl_t6", "name": "Tawny Cypress"}, "character_and_episodes": [{"url": "/title/tt1842530/characters/nm0194241?ref_=tt_cl_t6", "name": "Cherie Rollins-Murray"}, {"url": "#", "name": "26 episodes, 2013-2014"}]}, {"actor": {"@type": "Person", "url": "/name/nm0710271/?ref_=tt_cl_t8", "name": "Kevin Rankin"}, "character_and_episodes": [{"url": "/title/tt1842530/characters/nm0710271?ref_=tt_cl_t8", "name": "Roe Saunders"}, {"url": "#", "name": "22 episodes, 2011-2012"}]}]}