{"@context": "http://schema.org", "@type": "TVSeries", "url": "/title/tt7631146/", "name": "The Split", "image": "https://m.media-amazon.com/images/M/MV5BNjkzZGYwYmQtMGE5OC00MWIxLTg1YTktYTIyMjE3OTA4MWMzXkEyXkFqcGdeQXVyNzQ5MzY0NjM@._V1_.jpg", "genre": "Drama", "contentRating": "TV-MA", "actor": [{"@type": "Person", "url": "/name/nm0908070/", "name": "Nicola Walker"}, {"@type": "Person", "url": "/name/nm0542118/", "name": "Stephen Mangan"}, {"@type": "Person", "url": "/name/nm2118257/", "name": "Annabel Scholey"}, {"@type": "Person", "url": "/name/nm2484725/", "name": "Fiona Button"}], "creator": [{"@type": "Person", "url": "/name/nm0604448/", "name": "Abi Morgan"}, {"@type": "Organization", "url": "/company/co0571744/"}], "description": "The Split is a TV series starring Nicola Walker, Stephen Mangan, and Annabel Scholey. The Defoes, a family of female divorce lawyers, are forced to face their past following the return of their estranged father after a 30 year...", "datePublished": "2018-04-24", "keywords": "london england,divorce lawyer,estranged father,absence,marriage", "aggregateRating": {"@type": "AggregateRating", "ratingCount": 3800, "bestRating": "10.0", "worstRating": "1.0", "ratingValue": "7.7"}, "review": {"@type": "Review", "itemReviewed": {"@type": "CreativeWork", "url": "/title/tt7631146/"}, "author": {"@type": "Person", "name": "wadlowa"}, "dateCreated": "2020-02-13", "inLanguage": "English", "name": "Series 2 is better than 1 which is a first!", "reviewBody": "Love this!!!! Have just binge watched all 6 episodes of series two. Better than series one which is unusual ..... cried my eyes out at the end of episode 6. Aaaargh when is series three coming out!?!", "reviewRating": {"@type": "Rating", "worstRating": "1", "bestRating": "10", "ratingValue": "8"}}, "trailer": {"@type": "VideoObject", "name": "The Split", "embedUrl": "/video/imdb/vi3544823833", "thumbnail": {"@type": "ImageObject", "contentUrl": "https://m.media-amazon.com/images/M/MV5BMWVkYzkwODEtOTU5Mi00NDc2LTlhYjYtMzJlNmNkYTZjNmFhXkEyXkFqcGdeQXRodW1ibmFpbC1pbml0aWFsaXplcg@@._V1_.jpg"}, "thumbnailUrl": "https://m.media-amazon.com/images/M/MV5BMWVkYzkwODEtOTU5Mi00NDc2LTlhYjYtMzJlNmNkYTZjNmFhXkEyXkFqcGdeQXRodW1ibmFpbC1pbml0aWFsaXplcg@@._V1_.jpg", "uploadDate": "2018-05-07T22:08:54Z"}, "cast_and_character": [{"actor": {"@type": "Person", "url": "/name/nm0908070/?ref_=tt_cl_t1", "name": "Nicola Walker"}, "character_and_episodes": [{"url": "/title/tt7631146/characters/nm0908070?ref_=tt_cl_t1", "name": "Hannah Stern"}, {"url": "#", "name": "13 episodes, 2018-2020"}]}, {"actor": {"@type": "Person", "url": "/name/nm0277525/?ref_=tt_cl_t3", "name": "Deborah Findlay"}, "character_and_episodes": [{"url": "/title/tt7631146/characters/nm0277525?ref_=tt_cl_t3", "name": "Ruth"}, {"url": "#", "name": "12 episodes, 2018-2020"}]}, {"actor": {"@type": "Person", "url": "/name/nm2118257/?ref_=tt_cl_t5", "name": "Annabel Scholey"}, "character_and_episodes": [{"url": "/title/tt7631146/characters/nm2118257?ref_=tt_cl_t5", "name": "Nina"}, {"url": "#", "name": "12 episodes, 2018-2020"}]}, {"actor": {"@type": "Person", "url": "/name/nm6299413/?ref_=tt_cl_t7", "name": "Elizabeth Roberts"}, "character_and_episodes": [{"url": "/title/tt7631146/characters/nm6299413?ref_=tt_cl_t7", "name": "Liv Stern"}, {"url": "#", "name": "12 episodes, 2018-2020"}]}, {"actor": {"@type": "Person", "url": "/name/nm8215952/?ref_=tt_cl_t9", "name": "Toby Oliver"}, "character_and_episodes": [{"url": "/title/tt7631146/characters/nm8215952?ref_=tt_cl_t9", "name": "Vinnie Stern"}, {"url": "#", "name": "12 episodes, 2018-2020"}]}, {"actor": {"@type": "Person", "url": "/name/nm4089168/?ref_=tt_cl_t11", "name": "Ellora Torchia"}, "character_and_episodes": [{"url": "/title/tt7631146/characters/nm4089168?ref_=tt_cl_t11", "name": "Maggie"}, {"url": "#", "name": "12 episodes, 2018-2020"}]}, {"actor": {"@type": "Person", "url": "/name/nm7287176/?ref_=tt_cl_t13", "name": "Ty Hurley"}, "character_and_episodes": [{"url": "/title/tt7631146/characters/nm7287176?ref_=tt_cl_t13", "name": "Corporate Receptionist"}, {"url": "#", "name": "1 episode, 2018-2020"}]}, {"actor": {"@type": "Person", "url": "/name/nm2509609/?ref_=tt_cl_t15", "name": "Doc Brown"}, "character_and_episodes": [{"url": "/title/tt7631146/characters/nm2509609?ref_=tt_cl_t15", "name": "Richie Hansen"}, {"url": "#", "name": "6 episodes, 2020"}]}, {"actor": {"@type": "Person", "url": "/name/nm9580667/?ref_=tt_cl_t17", "name": "Afolabi Alli"}, "character_and_episodes": [{"url": "/title/tt7631146/characters/nm9580667?ref_=tt_cl_t17", "name": "Sean Bainbridge"}, {"url": "#", "name": "6 episodes, 2018"}]}, {"actor": {"@type": "Person", "url": "/name/nm3729877/?ref_=tt_cl_t19", "name": "Damien Molony"}, "character_and_episodes": [{"url": "/title/tt7631146/characters/nm3729877?ref_=tt_cl_t19", "name": "Tyler"}, {"url": "#", "name": "6 episodes, 2020"}]}, {"actor": {"@type": "Person", "url": "/name/nm0867017/?ref_=tt_cl_t21", "name": "Stephen Tompkinson"}, "character_and_episodes": [{"url": "/title/tt7631146/characters/nm0867017?ref_=tt_cl_t21", "name": "Davey"}, {"url": "#", "name": "6 episodes, 2018"}]}, {"actor": {"@type": "Person", "url": "/name/nm1506183/?ref_=tt_cl_t23", "name": "Kobna Holdbrook-Smith"}, "character_and_episodes": [{"url": "/title/tt7631146/characters/nm1506183?ref_=tt_cl_t23", "name": "Glen Peters"}, {"url": "#", "name": "6 episodes, 2018"}]}, {"actor": {"@type": "Person", "url": "/name/nm0542118/?ref_=tt_cl_t2", "name": "Stephen Mangan"}, "character_and_episodes": [{"url": "/title/tt7631146/characters/nm0542118?ref_=tt_cl_t2", "name": "Nathan"}, {"url": "#", "name": "12 episodes, 2018-2020"}]}, {"actor": {"@type": "Person", "url": "/name/nm0040038/?ref_=tt_cl_t4", "name": "Barry Atsma"}, "character_and_episodes": [{"url": "/title/tt7631146/characters/nm0040038?ref_=tt_cl_t4", "name": "Christie"}, {"url": "#", "name": "12 episodes, 2018-2020"}]}, {"actor": {"@type": "Person", "url": "/name/nm2484725/?ref_=tt_cl_t6", "name": "Fiona Button"}, "character_and_episodes": [{"url": "/title/tt7631146/characters/nm2484725?ref_=tt_cl_t6", "name": "Rose"}, {"url": "#", "name": "12 episodes, 2018-2020"}]}, {"actor": {"@type": "Person", "url": "/name/nm1030244/?ref_=tt_cl_t8", "name": "Chukwudi Iwuji"}, "character_and_episodes": [{"url": "/title/tt7631146/characters/nm1030244?ref_=tt_cl_t8", "name": "Zander"}, {"url": "#", "name": "12 episodes, 2018-2020"}]}, {"actor": {"@type": "Person", "url": "/name/nm6452890/?ref_=tt_cl_t10", "name": "Mollie Cowen"}, "character_and_episodes": [{"url": "/title/tt7631146/characters/nm6452890?ref_=tt_cl_t10", "name": "Tilly Stern"}, {"url": "#", "name": "12 episodes, 2018-2020"}]}, {"actor": {"@type": "Person", "url": "/name/nm1454287/?ref_=tt_cl_t12", "name": "Rudi Dharmalingam"}, "character_and_episodes": [{"url": "/title/tt7631146/characters/nm1454287?ref_=tt_cl_t12", "name": "James"}, {"url": "#", "name": "12 episodes, 2018-2020"}]}, {"actor": {"@type": "Person", "url": "/name/nm0014756/?ref_=tt_cl_t14", "name": "Donna Air"}, "character_and_episodes": [{"url": "/title/tt7631146/characters/nm0014756?ref_=tt_cl_t14", "name": "Fi Hansen"}, {"url": "#", "name": "6 episodes, 2020"}]}, {"actor": {"@type": "Person", "url": "/name/nm0842934/?ref_=tt_cl_t16", "name": "Meera Syal"}, "character_and_episodes": [{"url": "/title/tt7631146/characters/nm0842934?ref_=tt_cl_t16", "name": "Goldie"}, {"url": "#", "name": "6 episodes, 2018"}]}, {"actor": {"@type": "Person", "url": "/name/nm11377869/?ref_=tt_cl_t18", "name": "Moses Walcott"}, "character_and_episodes": [{"url": "/title/tt7631146/characters/nm11377869?ref_=tt_cl_t18", "name": "Dexter Hansen"}, {"url": "#", "name": "6 episodes, 2020"}]}, {"actor": {"@type": "Person", "url": "/name/nm3072466/?ref_=tt_cl_t20", "name": "Amaka Okafor"}, "character_and_episodes": [{"url": "/title/tt7631146/characters/nm3072466?ref_=tt_cl_t20", "name": "Chloe"}, {"url": "#", "name": "6 episodes, 2020"}]}, {"actor": {"@type": "Person", "url": "/name/nm0372117/?ref_=tt_cl_t22", "name": "Anthony Head"}, "character_and_episodes": [{"url": "/title/tt7631146/characters/nm0372117?ref_=tt_cl_t22", "name": "Oscar"}, {"url": "#", "name": "6 episodes, 2018"}]}, {"actor": {"@type": "Person", "url": "/name/nm0568400/?ref_=tt_cl_t24", "name": "Ian McElhinney"}, "character_and_episodes": [{"url": "/title/tt7631146/characters/nm0568400?ref_=tt_cl_t24", "name": "Prof Ronnie"}, {"url": "#", "name": "6 episodes, 2020"}]}]}