{"@context": "http://schema.org", "@type": "TVSeries", "url": "/title/tt2234222/", "name": "Orphan Black", "image": "https://m.media-amazon.com/images/M/MV5BZjM1ZTVlMGYtNjVkZS00OGMzLWFjMmYtYTE3NjJhZDRlODY3XkEyXkFqcGdeQXVyNzA5NjUyNjM@._V1_.jpg", "genre": ["Action", "Drama", "Sci-Fi"], "contentRating": "TV-MA", "actor": [{"@type": "Person", "url": "/name/nm1137209/", "name": "Tatiana Maslany"}, {"@type": "Person", "url": "/name/nm1851313/", "name": "Dylan Bruce"}, {"@type": "Person", "url": "/name/nm2849998/", "name": "Jordan Gavaris"}, {"@type": "Person", "url": "/name/nm0359322/", "name": "Kevin Hanchard"}], "creator": [{"@type": "Person", "url": "/name/nm1528935/", "name": "Kim Coghill"}, {"@type": "Person", "url": "/name/nm3784672/", "name": "Andrew De Angelis"}, {"@type": "Person", "url": "/name/nm3709826/", "name": "Jeff Detsky"}, {"@type": "Person", "url": "/name/nm0269502/", "name": "John Fawcett"}, {"@type": "Person", "url": "/name/nm4166033/", "name": "Adam Higgs"}, {"@type": "Person", "url": "/name/nm1289249/", "name": "Alex Levine"}, {"@type": "Person", "url": "/name/nm4839522/", "name": "Bob Mackowycz Jr."}, {"@type": "Person", "url": "/name/nm0543919/", "name": "Graeme Manson"}, {"@type": "Person", "url": "/name/nm3927959/", "name": "Elize Morgan"}, {"@type": "Person", "url": "/name/nm3665655/", "name": "Peter Rowley"}, {"@type": "Person", "url": "/name/nm1372017/", "name": "Rebecca Sernasie"}, {"@type": "Organization", "url": "/company/co0069372/"}], "description": "Orphan Black is a TV series starring Tatiana Maslany, Dylan Bruce, and Jordan Gavaris. A streetwise hustler is pulled into a compelling conspiracy after witnessing the suicide of a girl who looks just like her.", "datePublished": "2013-03-30", "keywords": "female protagonist,suicide,brainwashed assassin,mad scientist,genetic enhancement", "aggregateRating": {"@type": "AggregateRating", "ratingCount": 102759, "bestRating": "10.0", "worstRating": "1.0", "ratingValue": "8.3"}, "review": {"@type": "Review", "itemReviewed": {"@type": "CreativeWork", "url": "/title/tt2234222/"}, "author": {"@type": "Person", "name": "blanche-2"}, "dateCreated": "2014-12-23", "inLanguage": "English", "name": "phenomenal", "reviewBody": "\"Orphan Black\" is a highly underrated series starring the woefully underrated Tatiana Maslany. What is the story there? This woman's name should be shouted from housetops. She should be heralded as the next Meryl Streep.\n\nLike others on this board, I don't want to say too much and give the story away. In order to see what makes Maslany so amazing, you need to watch the show.\n\nThe story is full of twists and turns. In the beginning, we see a young woman, Sarah (Maslany) witness the suicide of a woman on the subway tracks. A fast thinker who lives on the edge, Sarah grabs her purse and her identity. It goes from there.\n\nThe series is peppered with interesting characters, including Jordan Gavaris as Sarah's gay hustler brother; Maria Doyle Kennedy as Mrs. S, Matt Frewer as Dr. Leeke, and many others. I'll just name the characters - they're all marvelous: Cosima, Alison, Rachel, Helena, Tony, etc.\n\nDon't miss this, and don't ask me why everybody's not talking about it.", "reviewRating": {"@type": "Rating", "worstRating": "1", "bestRating": "10", "ratingValue": "10"}}, "trailer": {"@type": "VideoObject", "name": "Orphan Black - Season 3 teaser", "embedUrl": "/video/imdb/vi1926017305", "thumbnail": {"@type": "ImageObject", "contentUrl": "https://m.media-amazon.com/images/M/MV5BMTcyMzA2NzgzM15BMl5BanBnXkFtZTgwNzk3MDIwNTE@._V1_.jpg"}, "thumbnailUrl": "https://m.media-amazon.com/images/M/MV5BMTcyMzA2NzgzM15BMl5BanBnXkFtZTgwNzk3MDIwNTE@._V1_.jpg", "description": "Sarah comes face to face with a new Castor clone in this sneak peek of Episode 1, which premieres Saturday, April 18th at 9/8c on BBC America.", "uploadDate": "2015-03-26T07:33:34Z"}, "cast_and_character": [{"actor": {"@type": "Person", "url": "/name/nm1137209/?ref_=tt_cl_t1", "name": "Tatiana Maslany"}, "character_and_episodes": [{"url": "/title/tt2234222/characters/nm1137209?ref_=tt_cl_t1", "name": "Sarah Manning"}, {"url": "#", "name": "50 episodes, 2013-2017"}]}, {"actor": {"@type": "Person", "url": "/name/nm0448204/?ref_=tt_cl_t3", "name": "Maria Doyle Kennedy"}, "character_and_episodes": [{"url": "/title/tt2234222/characters/nm0448204?ref_=tt_cl_t3", "name": "Siobhan Sadler"}, {"url": "#", "name": "50 episodes, 2013-2017"}]}, {"actor": {"@type": "Person", "url": "/name/nm0359322/?ref_=tt_cl_t5", "name": "Kevin Hanchard"}, "character_and_episodes": [{"url": "/title/tt2234222/characters/nm0359322?ref_=tt_cl_t5", "name": "Detective Art Bell"}, {"url": "#", "name": "44 episodes, 2013-2017"}]}, {"actor": {"@type": "Person", "url": "/name/nm4602731/?ref_=tt_cl_t7", "name": "Josh Vokey"}, "character_and_episodes": [{"url": "/title/tt2234222/characters/nm4602731?ref_=tt_cl_t7", "name": "Scott"}, {"url": "#", "name": "38 episodes, 2013-2017"}]}, {"actor": {"@type": "Person", "url": "/name/nm2903342/?ref_=tt_cl_t9", "name": "Evelyne Brochu"}, "character_and_episodes": [{"url": "/title/tt2234222/characters/nm2903342?ref_=tt_cl_t9", "name": "Delphine Cormier"}, {"url": "#", "name": "29 episodes, 2013-2017"}]}, {"actor": {"@type": "Person", "url": "/name/nm2849998/?ref_=tt_cl_t2", "name": "Jordan Gavaris"}, "character_and_episodes": [{"url": "/title/tt2234222/characters/nm2849998?ref_=tt_cl_t2", "name": "Felix Dawkins"}, {"url": "#", "name": "50 episodes, 2013-2017"}]}, {"actor": {"@type": "Person", "url": "/name/nm2106870/?ref_=tt_cl_t4", "name": "Kristian Bruun"}, "character_and_episodes": [{"url": "/title/tt2234222/characters/nm2106870?ref_=tt_cl_t4", "name": "Donnie Hendrix"}, {"url": "#", "name": "45 episodes, 2013-2017"}]}, {"actor": {"@type": "Person", "url": "/name/nm4585214/?ref_=tt_cl_t6", "name": "Skyler Wexler"}, "character_and_episodes": [{"url": "/title/tt2234222/characters/nm4585214?ref_=tt_cl_t6", "name": "Kira Manning"}, {"url": "#", "name": "39 episodes, 2013-2017"}]}, {"actor": {"@type": "Person", "url": "/name/nm2826395/?ref_=tt_cl_t8", "name": "Ari Millen"}, "character_and_episodes": [{"url": "/title/tt2234222/characters/nm2826395?ref_=tt_cl_t8", "name": "Mark Rollins"}, {"url": "#", "name": "36 episodes, 2014-2017"}]}, {"actor": {"@type": "Person", "url": "/name/nm1851313/?ref_=tt_cl_t10", "name": "Dylan Bruce"}, "character_and_episodes": [{"url": "/title/tt2234222/characters/nm1851313?ref_=tt_cl_t10", "name": "Paul Dierden"}, {"url": "#", "name": "28 episodes, 2013-2016"}]}], "details": {"Country": ["Canada"], "Language": ["English"], "Release Date": ["30 March 2013 (USA)"], "Also Known As": ["Orphan Black"], "Filming Locations": ["Toronto, Ontario, Canada"], "Production Co": ["Temple Street Productions"], "Runtime": ["44 min", "60 min"], "Sound Mix": ["Stereo", "Dolby Digital"], "Aspect Ratio": ["16:9 HD"]}}